LSH_LINK/__init__.py
LSHlink/__init__.py
LSH_LINK-0.1.dist-info/LICENSE
LSH_LINK-0.1.dist-info/METADATA
LSH_LINK-0.1.dist-info/WHEEL
LSH_LINK-0.1.dist-info/top_level.txt
LSH_LINK-0.1.dist-info/RECORD
