Metadata-Version: 2.1
Name: LSH-LINK
Version: 0.1
Summary: Base on Fast agglomerative hierarchical clustering algorithm using Locality-Sensitive Hashing,  we develop algorithm in Python.
Home-page: https://github.com/Brian1357/STA663-Project-LSHLink
Author: Boyang Pan & Nancun Li
Author-email: nancun.li@duke.edu
License: UNKNOWN
Platform: UNKNOWN
Requires-Dist: sklearn (>=0.0)
Requires-Dist: numpy (>=1.18.1)
Requires-Dist: matplotlib (>=3.1.3)
Requires-Dist: scipy (>=1.4.1)
